[{"Author":"TechGuide Team","Name":"TechGuide","InternalName":"TechGuide","AssemblyVersion":"1.0.0.38","Description":"卫月战斗循环插件 - 从 RebornBuddy 迁移到 Dalamud","Punchline":"FFXIV 战斗辅助","ApplicableVersion":"any","RepoUrl":"https://github.com/sortec001/tech-guide-repo","Changelog":"普通敌人：未勾选则小怪禁用 DoT/爆发，勾选才按血量阈值；镰刀/武士已接入","DalamudApiLevel":15,"LoadPriority":0,"IsHide":"False","IsTestingExclusive":"False","LastUpdate":"1784340732","DownloadLinkInstall":"https://github.com/sortec001/tech-guide-repo/raw/main/release/TechGuide/latest.zip","DownloadLinkTesting":"https://github.com/sortec001/tech-guide-repo/raw/main/release/TechGuide/latest.zip","DownloadLinkUpdate":"https://github.com/sortec001/tech-guide-repo/raw/main/release/TechGuide/latest.zip"}]
